async_rutube_downloader/__init__.py
async_rutube_downloader/__main__.py
async_rutube_downloader/playlist.py
async_rutube_downloader/run_cli.py
async_rutube_downloader/run_ui.py
async_rutube_downloader/rutube_downloader.py
async_rutube_downloader/settings.py
async_rutube_downloader/ui.py
async_rutube_downloader/utils/create_session.py
async_rutube_downloader/utils/decorators.py
async_rutube_downloader/utils/descriptors.py
async_rutube_downloader/utils/exceptions.py
async_rutube_downloader/utils/interfaces.py
async_rutube_downloader/utils/locale.py
async_rutube_downloader/utils/logger.py
async_rutube_downloader/utils/miscellaneous.py
async_rutube_downloader/utils/type_hints.py
async_rutube_downloader/utils/validators.py
async_rutube_downloader-1.4.2.dist-info/LICENSE
async_rutube_downloader-1.4.2.dist-info/METADATA
async_rutube_downloader-1.4.2.dist-info/WHEEL
async_rutube_downloader-1.4.2.dist-info/entry_points.txt
async_rutube_downloader-1.4.2.dist-info/RECORD
