Metadata-Version: 2.3
Name: async_rutube_downloader
Version: 1.4.2
Summary: download video from RuTube
Author: Miron Sadykov
Author-email: MironSadykov@yandex.ru
Requires-Python: >=3.12,<3.13
Classifier: Programming Language :: Python :: 3
Classifier: Operating System :: OS Independent
Classifier: License :: OSI Approved :: MIT License
Provides-Extra: dev
Requires-Dist: aiofiles (>=24.1.0,<25.0.0)
Requires-Dist: aiohttp (>=3.11.6,<4.0.0)
Requires-Dist: coveralls (>=4.0.1,<5.0.0) ; extra == "dev"
Requires-Dist: customtkinter (>=5.2.2,<6.0.0)
Requires-Dist: m3u8 (>=6.0.0,<7.0.0)
Requires-Dist: pre-commit (>=4.1.0,<5.0.0) ; extra == "dev"
Requires-Dist: pyinstaller (>=6.11.1,<7.0.0) ; extra == "dev"
Requires-Dist: pytest (>=8.3.3,<9.0.0) ; extra == "dev"
Requires-Dist: pytest-asyncio (>=0.24.0,<1.0.0) ; extra == "dev"
Requires-Dist: pytest-cov (>=6.0.0,<7.0.0) ; extra == "dev"
Requires-Dist: python-slugify (>=8.0.4,<9.0.0)
Requires-Dist: ruff (>=0.7.4,<1.0.0) ; extra == "dev"
Requires-Dist: types-aiofiles (>=24.1.0.20240626,<25.0.0) ; extra == "dev"
Requires-Dist: types-m3u8 (>=6.0.0.20241002,<7.0.0) ; extra == "dev"
Project-URL: Homepage, https://github.com/Reagent992/async_rutube_downloader
Project-URL: Issues, https://github.com/Reagent992/async_rutube_downloader/issues
